{"all_tests":[{"browser":"brave","capabilities":{"acceptInsecureCerts":false,"browserName":"chrome","browserVersion":"93.0.4577.58","chrome":{"chromedriverVersion":"92.0.4515.107 (87a818b10553a07434ea9e2b6dccf3cbe7895134-refs/branch-heads/4515@{#1634})","userDataDir":"/tmp/.com.google.Chrome.6K32Fv"},"goog:chromeOptions":{"debuggerAddress":"localhost:9222"},"networkConnectionEnabled":false,"pageLoadStrategy":"normal","platformName":"linux","proxy":{},"setWindowRect":true,"strictFileInteractability":false,"timeouts":{"implicit":0,"pageLoad":300000,"script":30000},"unhandledPromptBehavior":"dismiss and notify","webauthn:extension:credBlob":true,"webauthn:extension:largeBlob":true,"webauthn:virtualAuthenticators":true},"testResults":null,"timeStarted":"2021-09-02T20:55:30.474Z","incognito":true}],"git":"0a0693482ad31847adaab7ad81dd88ba854562f2","timeStarted":"2021-09-02T20:55:30.390Z","timeStopped":"2021-09-02T20:55:39.890Z"}